{"project_chat_guide.md":"7468e24b","essay_2022.md":"62a6f963","essay_front-endserviceframework.md":"a80cf8d1","essay_githubaction.md":"98bf003a","essay_guide.md":"dd24bc03","essay_infrastructure.md":"878a81b0","essay_task-lists.md":"5b518c31","essay_monorepo.md":"05d72219","project_guide.md":"2b2cd697","studydoc_algorithm_linkedlist_mylinkedlist.md":"73ee0a26","studydoc_algorithm_array_array.md":"248ae0a7","theory_ts_guide.md":"9bcffe77","studydoc_algorithm_array_generatematrix.md":"615f7894","memo_guide.md":"af145d07","studydoc_algorithm_linkedlist_removeelements.md":"b7cdaa01","index.md":"0c8657ab","studydoc_algorithm_array_binary.md":"71973a7f","studydoc_algorithm_linkedlist_reverselist.md":"a51963a8","essay_uselist.md":"9111436b","studydoc_algorithm_array_sortedsquares.md":"e25d27ea","studydoc_algorithm_guide.md":"ade2eab0","studydoc_algorithm_linkedlist_guide.md":"2d9bbded","studydoc_algorithm_linkedlist_swappairs.md":"b9f004dd","studydoc_guide.md":"83a4ea8d","theory_guide.md":"0963c56f","studydoc_algorithm_linkedlist_detectcycle.md":"f61fdfa9","studydoc_algorithm_array_minsubarraylen.md":"5933b237","theory_vue3_code_one.md":"6144c22b","theory_vue3_guide.md":"c92ed6ce","tools_algolia.md":"186d9b0f","tools_guide.md":"813a82d6","project_chat_uploder.md":"783ffabd","studydoc_algorithm_array_removeelement.md":"a5a8f2c5","theory_vue3_analysis_reactive.md":"194ffb7f","theory_vue3_analysis_vnodetodom.md":"ad964f68"}
