{"essay_task-lists.md":"a9afb229","essay_uselist.md":"264fb82a","studydoc_guide.md":"ec3f3a14","theory_guide.md":"0b81d58c","theory_ts_guide.md":"50de1c53","studydoc_algorithm_array_minsubarraylen.md":"1a39ea55","studydoc_algorithm_array_removeelement.md":"d4754365","essay_2022.md":"f1e2f449","essay_front-endserviceframework.md":"216cf8f6","essay_guide.md":"ecc71385","essay_infrastructure.md":"0287fe04","index.md":"6d4a3e60","memo_guide.md":"f2492f14","project_chat_guide.md":"d49640d6","project_chat_uploder.md":"1f5a0c15","project_guide.md":"5bc998fb","studydoc_algorithm_linkedlist_guide.md":"3fd34be5","essay_monorepo.md":"fa1d502c","studydoc_algorithm_array_array.md":"27764338","studydoc_algorithm_array_generatematrix.md":"016c1733","studydoc_algorithm_array_sortedsquares.md":"737fcf7d","studydoc_algorithm_array_binary.md":"62bd3cb8","theory_vue3_code_one.md":"af9d2cda","theory_vue3_guide.md":"dc2628de","studydoc_algorithm_guide.md":"ef681899","theory_vue3_analysis_vnodetodom.md":"d49967ad","tools_guide.md":"6c288adc","tools_algolia.md":"7d622746"}
